sf_quant/__init__.py
sf_quant/backtester/__init__.py
sf_quant/backtester/parallel.py
sf_quant/backtester/sequential.py
sf_quant/data/__init__.py
sf_quant/data/_factors.py
sf_quant/data/_tables.py
sf_quant/data/_views.py
sf_quant/data/assets.py
sf_quant/data/benchmark.py
sf_quant/data/covariance_matrix.py
sf_quant/data/covariances.py
sf_quant/data/crsp_daily.py
sf_quant/data/crsp_monthly.py
sf_quant/data/crsp_v2_daily.py
sf_quant/data/crsp_v2_monthly.py
sf_quant/data/exposures.py
sf_quant/data/factors.py
sf_quant/data/fama_french.py
sf_quant/optimizer/__init__.py
sf_quant/optimizer/constraints.py
sf_quant/optimizer/optimizers.py
sf_quant/performance/__init__.py
sf_quant/performance/charts.py
sf_quant/performance/drawdown.py
sf_quant/performance/ics.py
sf_quant/performance/leverage.py
sf_quant/performance/returns.py
sf_quant/performance/tables.py
sf_quant/schema/__init__.py
sf_quant/schema/alpha_schema.py
sf_quant/schema/drawdown_schema.py
sf_quant/schema/fama_french_schema.py
sf_quant/schema/ic_schema.py
sf_quant/schema/leverage_schema.py
sf_quant/schema/portfolio_schema.py
sf_quant/schema/returns_schema.py
sf_quant-0.1.16.dist-info/METADATA
sf_quant-0.1.16.dist-info/WHEEL
sf_quant-0.1.16.dist-info/RECORD
