Metadata-Version: 2.4
Name: sf-quant
Version: 0.1.16
Summary: Python package for Silver Fund quant team research and trading tools.
Author-email: Andrew Hall <andrewmartinhall2@gmail.com>
Requires-Python: <3.14,>=3.11
Requires-Dist: cvxpy>=1.7.2
Requires-Dist: dataframely>=1.14.0
Requires-Dist: matplotlib>=3.10.5
Requires-Dist: numpy>=2.3.2
Requires-Dist: polars>=1.32.3
Requires-Dist: python-dotenv>=1.1.1
Requires-Dist: ray>=2.49.0
Requires-Dist: seaborn>=0.13.2
Requires-Dist: tqdm>=4.67.1
